<?xml version="1.0" encoding="UTF-8"?>
<MetaDataObject xmlns="http://v8.1c.ru/8.3/MDClasses" xmlns:app="http://v8.1c.ru/8.2/managed-application/core" xmlns:cfg="http://v8.1c.ru/8.1/data/enterprise/current-config" xmlns:cmi="http://v8.1c.ru/8.2/managed-application/cmi" xmlns:ent="http://v8.1c.ru/8.1/data/enterprise" xmlns:lf="http://v8.1c.ru/8.2/managed-application/logform" xmlns:style="http://v8.1c.ru/8.1/data/ui/style" xmlns:sys="http://v8.1c.ru/8.1/data/ui/fonts/system" xmlns:v8="http://v8.1c.ru/8.1/data/core" xmlns:v8ui="http://v8.1c.ru/8.1/data/ui" xmlns:web="http://v8.1c.ru/8.1/data/ui/colors/web" xmlns:win="http://v8.1c.ru/8.1/data/ui/colors/windows" xmlns:xen="http://v8.1c.ru/8.3/xcf/enums" xmlns:xpr="http://v8.1c.ru/8.3/xcf/predef" xmlns:xr="http://v8.1c.ru/8.3/xcf/readable" xmlns:xs="http://www.w3.org/2001/XMLSchema" xmlns:xsi="http://www.w3.org/2001/XMLSchema-instance" version="2.11">
	<Constant uuid="64c76e86-91ae-4fd9-a927-4d9ea83f261e">
		<InternalInfo>
			<xr:GeneratedType name="ConstantManager.ДатаОбновленияКешаТарификации" category="Manager">
				<xr:TypeId>26ccf82c-6127-4d8a-a131-4deb18e57782</xr:TypeId>
				<xr:ValueId>44d1901c-503a-4567-b30a-2d6ec2d5d690</xr:ValueId>
			</xr:GeneratedType>
			<xr:GeneratedType name="ConstantValueManager.ДатаОбновленияКешаТарификации" category="ValueManager">
				<xr:TypeId>b5e96806-0305-4e7a-86e5-ea60fb2d5bb8</xr:TypeId>
				<xr:ValueId>8742e8a2-b267-42e1-9716-5afe39838509</xr:ValueId>
			</xr:GeneratedType>
			<xr:GeneratedType name="ConstantValueKey.ДатаОбновленияКешаТарификации" category="ValueKey">
				<xr:TypeId>1610596f-e8dd-5806-bcf0-3e3878361b6c</xr:TypeId>
				<xr:ValueId>3f4bb553-8b86-5d7d-8684-73055062a9c1</xr:ValueId>
			</xr:GeneratedType>
		</InternalInfo>
		<Properties>
			<Name>ДатаОбновленияКешаТарификации</Name>
			<Synonym>
				<v8:item>
					<v8:lang>ru</v8:lang>
					<v8:content>Дата обновления кеша тарификации</v8:content>
				</v8:item>
			</Synonym>
			<Comment/>
			<Type>
				<v8:Type>xs:dateTime</v8:Type>
				<v8:DateQualifiers>
					<v8:DateFractions>DateTime</v8:DateFractions>
				</v8:DateQualifiers>
			</Type>
			<UseStandardCommands>true</UseStandardCommands>
			<DefaultForm/>
			<ExtendedPresentation/>
			<Explanation/>
			<PasswordMode>false</PasswordMode>
			<Format/>
			<EditFormat/>
			<ToolTip/>
			<MarkNegatives>false</MarkNegatives>
			<Mask/>
			<MultiLine>false</MultiLine>
			<ExtendedEdit>false</ExtendedEdit>
			<MinValue xsi:nil="true"/>
			<MaxValue xsi:nil="true"/>
			<FillChecking>DontCheck</FillChecking>
			<ChoiceFoldersAndItems>Items</ChoiceFoldersAndItems>
			<ChoiceParameterLinks/>
			<ChoiceParameters/>
			<QuickChoice>Auto</QuickChoice>
			<ChoiceForm/>
			<LinkByType/>
			<ChoiceHistoryOnInput>Auto</ChoiceHistoryOnInput>
			<DataLockControlMode>Managed</DataLockControlMode>
			<DataHistory>DontUse</DataHistory>
			<UpdateDataHistoryImmediatelyAfterWrite>false</UpdateDataHistoryImmediatelyAfterWrite>
			<ExecuteAfterWriteDataHistoryVersionProcessing>false</ExecuteAfterWriteDataHistoryVersionProcessing>
		</Properties>
	</Constant>
</MetaDataObject>