<?xml version="1.0" encoding="UTF-8"?>
<MetaDataObject xmlns="http://v8.1c.ru/8.3/MDClasses" xmlns:app="http://v8.1c.ru/8.2/managed-application/core" xmlns:cfg="http://v8.1c.ru/8.1/data/enterprise/current-config" xmlns:cmi="http://v8.1c.ru/8.2/managed-application/cmi" xmlns:ent="http://v8.1c.ru/8.1/data/enterprise" xmlns:lf="http://v8.1c.ru/8.2/managed-application/logform" xmlns:style="http://v8.1c.ru/8.1/data/ui/style" xmlns:sys="http://v8.1c.ru/8.1/data/ui/fonts/system" xmlns:v8="http://v8.1c.ru/8.1/data/core" xmlns:v8ui="http://v8.1c.ru/8.1/data/ui" xmlns:web="http://v8.1c.ru/8.1/data/ui/colors/web" xmlns:win="http://v8.1c.ru/8.1/data/ui/colors/windows" xmlns:xen="http://v8.1c.ru/8.3/xcf/enums" xmlns:xpr="http://v8.1c.ru/8.3/xcf/predef" xmlns:xr="http://v8.1c.ru/8.3/xcf/readable" xmlns:xs="http://www.w3.org/2001/XMLSchema" xmlns:xsi="http://www.w3.org/2001/XMLSchema-instance" version="2.11">
	<DocumentJournal uuid="039500ac-495c-41de-804e-913e07d19852">
		<InternalInfo>
			<xr:GeneratedType name="DocumentJournalSelection.ДокументыПоЗакупкам" category="Selection">
				<xr:TypeId>27a677ed-0abf-4083-a3d1-97a5119a7604</xr:TypeId>
				<xr:ValueId>f8a29cb6-62dd-40d8-90d2-9e590d78260c</xr:ValueId>
			</xr:GeneratedType>
			<xr:GeneratedType name="DocumentJournalList.ДокументыПоЗакупкам" category="List">
				<xr:TypeId>ce4a512d-141b-4a39-8850-15784b705a2d</xr:TypeId>
				<xr:ValueId>5aa8eb9c-1548-42db-9a2f-40851ca24bd2</xr:ValueId>
			</xr:GeneratedType>
			<xr:GeneratedType name="DocumentJournalManager.ДокументыПоЗакупкам" category="Manager">
				<xr:TypeId>bb626176-263e-4e49-b451-0cf76ec822f5</xr:TypeId>
				<xr:ValueId>608df4af-7a52-4f7b-a0eb-bd9f08d1c631</xr:ValueId>
			</xr:GeneratedType>
		</InternalInfo>
		<Properties>
			<Name>ДокументыПоЗакупкам</Name>
			<Synonym>
				<v8:item>
					<v8:lang>ru</v8:lang>
					<v8:content>Документы по закупкам</v8:content>
				</v8:item>
			</Synonym>
			<Comment/>
			<DefaultForm>DocumentJournal.ДокументыПоЗакупкам.Form.ФормаСписка</DefaultForm>
			<AuxiliaryForm/>
			<UseStandardCommands>true</UseStandardCommands>
			<RegisteredDocuments>
				<xr:Item xsi:type="xr:MDObjectRef">Document.ПриходнаяНакладная</xr:Item>
				<xr:Item xsi:type="xr:MDObjectRef">Document.ЗаказПоставщику</xr:Item>
				<xr:Item xsi:type="xr:MDObjectRef">Document.ДополнительныеРасходы</xr:Item>
				<xr:Item xsi:type="xr:MDObjectRef">Document.СчетФактураПолученный</xr:Item>
				<xr:Item xsi:type="xr:MDObjectRef">Document.СчетНаОплатуПоставщика</xr:Item>
				<xr:Item xsi:type="xr:MDObjectRef">Document.КорректировкаПоступления</xr:Item>
			</RegisteredDocuments>
			<IncludeHelpInContents>true</IncludeHelpInContents>
			<StandardAttributes>
				<xr:StandardAttribute name="Type">
					<xr:LinkByType/>
					<xr:FillChecking>DontCheck</xr:FillChecking>
					<xr:MultiLine>false</xr:MultiLine>
					<xr:FillFromFillingValue>false</xr:FillFromFillingValue>
					<xr:CreateOnInput>Auto</xr:CreateOnInput>
					<xr:MaxValue xsi:nil="true"/>
					<xr:ToolTip>
						<v8:item>
							<v8:lang>ru</v8:lang>
							<v8:content>Тип документа</v8:content>
						</v8:item>
					</xr:ToolTip>
					<xr:ExtendedEdit>false</xr:ExtendedEdit>
					<xr:Format/>
					<xr:ChoiceForm/>
					<xr:QuickChoice>Auto</xr:QuickChoice>
					<xr:ChoiceHistoryOnInput>Auto</xr:ChoiceHistoryOnInput>
					<xr:EditFormat/>
					<xr:PasswordMode>false</xr:PasswordMode>
					<xr:DataHistory>Use</xr:DataHistory>
					<xr:MarkNegatives>false</xr:MarkNegatives>
					<xr:MinValue xsi:nil="true"/>
					<xr:Synonym>
						<v8:item>
							<v8:lang>ru</v8:lang>
							<v8:content>Тип</v8:content>
						</v8:item>
					</xr:Synonym>
					<xr:Comment/>
					<xr:FullTextSearch>Use</xr:FullTextSearch>
					<xr:ChoiceParameterLinks/>
					<xr:FillValue xsi:nil="true"/>
					<xr:Mask/>
					<xr:ChoiceParameters/>
				</xr:StandardAttribute>
				<xr:StandardAttribute name="Ref">
					<xr:LinkByType/>
					<xr:FillChecking>DontCheck</xr:FillChecking>
					<xr:MultiLine>false</xr:MultiLine>
					<xr:FillFromFillingValue>false</xr:FillFromFillingValue>
					<xr:CreateOnInput>Auto</xr:CreateOnInput>
					<xr:MaxValue xsi:nil="true"/>
					<xr:ToolTip>
						<v8:item>
							<v8:lang>ru</v8:lang>
							<v8:content>Ссылка на документ</v8:content>
						</v8:item>
					</xr:ToolTip>
					<xr:ExtendedEdit>false</xr:ExtendedEdit>
					<xr:Format/>
					<xr:ChoiceForm/>
					<xr:QuickChoice>Auto</xr:QuickChoice>
					<xr:ChoiceHistoryOnInput>Auto</xr:ChoiceHistoryOnInput>
					<xr:EditFormat/>
					<xr:PasswordMode>false</xr:PasswordMode>
					<xr:DataHistory>Use</xr:DataHistory>
					<xr:MarkNegatives>false</xr:MarkNegatives>
					<xr:MinValue xsi:nil="true"/>
					<xr:Synonym>
						<v8:item>
							<v8:lang>ru</v8:lang>
							<v8:content>Ссылка</v8:content>
						</v8:item>
					</xr:Synonym>
					<xr:Comment/>
					<xr:FullTextSearch>Use</xr:FullTextSearch>
					<xr:ChoiceParameterLinks/>
					<xr:FillValue xsi:nil="true"/>
					<xr:Mask/>
					<xr:ChoiceParameters/>
				</xr:StandardAttribute>
				<xr:StandardAttribute name="Date">
					<xr:LinkByType/>
					<xr:FillChecking>DontCheck</xr:FillChecking>
					<xr:MultiLine>false</xr:MultiLine>
					<xr:FillFromFillingValue>false</xr:FillFromFillingValue>
					<xr:CreateOnInput>Auto</xr:CreateOnInput>
					<xr:MaxValue xsi:nil="true"/>
					<xr:ToolTip>
						<v8:item>
							<v8:lang>ru</v8:lang>
							<v8:content>Дата документа</v8:content>
						</v8:item>
					</xr:ToolTip>
					<xr:ExtendedEdit>false</xr:ExtendedEdit>
					<xr:Format/>
					<xr:ChoiceForm/>
					<xr:QuickChoice>Auto</xr:QuickChoice>
					<xr:ChoiceHistoryOnInput>Auto</xr:ChoiceHistoryOnInput>
					<xr:EditFormat/>
					<xr:PasswordMode>false</xr:PasswordMode>
					<xr:DataHistory>Use</xr:DataHistory>
					<xr:MarkNegatives>false</xr:MarkNegatives>
					<xr:MinValue xsi:nil="true"/>
					<xr:Synonym>
						<v8:item>
							<v8:lang>ru</v8:lang>
							<v8:content>Дата</v8:content>
						</v8:item>
					</xr:Synonym>
					<xr:Comment/>
					<xr:FullTextSearch>Use</xr:FullTextSearch>
					<xr:ChoiceParameterLinks/>
					<xr:FillValue xsi:nil="true"/>
					<xr:Mask/>
					<xr:ChoiceParameters/>
				</xr:StandardAttribute>
				<xr:StandardAttribute name="Posted">
					<xr:LinkByType/>
					<xr:FillChecking>DontCheck</xr:FillChecking>
					<xr:MultiLine>false</xr:MultiLine>
					<xr:FillFromFillingValue>false</xr:FillFromFillingValue>
					<xr:CreateOnInput>Auto</xr:CreateOnInput>
					<xr:MaxValue xsi:nil="true"/>
					<xr:ToolTip>
						<v8:item>
							<v8:lang>ru</v8:lang>
							<v8:content>Признак проведения документа</v8:content>
						</v8:item>
					</xr:ToolTip>
					<xr:ExtendedEdit>false</xr:ExtendedEdit>
					<xr:Format/>
					<xr:ChoiceForm/>
					<xr:QuickChoice>Auto</xr:QuickChoice>
					<xr:ChoiceHistoryOnInput>Auto</xr:ChoiceHistoryOnInput>
					<xr:EditFormat/>
					<xr:PasswordMode>false</xr:PasswordMode>
					<xr:DataHistory>Use</xr:DataHistory>
					<xr:MarkNegatives>false</xr:MarkNegatives>
					<xr:MinValue xsi:nil="true"/>
					<xr:Synonym>
						<v8:item>
							<v8:lang>ru</v8:lang>
							<v8:content>Проведен</v8:content>
						</v8:item>
					</xr:Synonym>
					<xr:Comment/>
					<xr:FullTextSearch>Use</xr:FullTextSearch>
					<xr:ChoiceParameterLinks/>
					<xr:FillValue xsi:nil="true"/>
					<xr:Mask/>
					<xr:ChoiceParameters/>
				</xr:StandardAttribute>
				<xr:StandardAttribute name="DeletionMark">
					<xr:LinkByType/>
					<xr:FillChecking>DontCheck</xr:FillChecking>
					<xr:MultiLine>false</xr:MultiLine>
					<xr:FillFromFillingValue>false</xr:FillFromFillingValue>
					<xr:CreateOnInput>Auto</xr:CreateOnInput>
					<xr:MaxValue xsi:nil="true"/>
					<xr:ToolTip>
						<v8:item>
							<v8:lang>ru</v8:lang>
							<v8:content>Пометка удаления документа</v8:content>
						</v8:item>
					</xr:ToolTip>
					<xr:ExtendedEdit>false</xr:ExtendedEdit>
					<xr:Format/>
					<xr:ChoiceForm/>
					<xr:QuickChoice>Auto</xr:QuickChoice>
					<xr:ChoiceHistoryOnInput>Auto</xr:ChoiceHistoryOnInput>
					<xr:EditFormat/>
					<xr:PasswordMode>false</xr:PasswordMode>
					<xr:DataHistory>Use</xr:DataHistory>
					<xr:MarkNegatives>false</xr:MarkNegatives>
					<xr:MinValue xsi:nil="true"/>
					<xr:Synonym>
						<v8:item>
							<v8:lang>ru</v8:lang>
							<v8:content>Пометка удаления</v8:content>
						</v8:item>
					</xr:Synonym>
					<xr:Comment/>
					<xr:FullTextSearch>Use</xr:FullTextSearch>
					<xr:ChoiceParameterLinks/>
					<xr:FillValue xsi:nil="true"/>
					<xr:Mask/>
					<xr:ChoiceParameters/>
				</xr:StandardAttribute>
				<xr:StandardAttribute name="Number">
					<xr:LinkByType/>
					<xr:FillChecking>DontCheck</xr:FillChecking>
					<xr:MultiLine>false</xr:MultiLine>
					<xr:FillFromFillingValue>false</xr:FillFromFillingValue>
					<xr:CreateOnInput>Auto</xr:CreateOnInput>
					<xr:MaxValue xsi:nil="true"/>
					<xr:ToolTip>
						<v8:item>
							<v8:lang>ru</v8:lang>
							<v8:content>Номер документа</v8:content>
						</v8:item>
					</xr:ToolTip>
					<xr:ExtendedEdit>false</xr:ExtendedEdit>
					<xr:Format/>
					<xr:ChoiceForm/>
					<xr:QuickChoice>Auto</xr:QuickChoice>
					<xr:ChoiceHistoryOnInput>Auto</xr:ChoiceHistoryOnInput>
					<xr:EditFormat/>
					<xr:PasswordMode>false</xr:PasswordMode>
					<xr:DataHistory>Use</xr:DataHistory>
					<xr:MarkNegatives>false</xr:MarkNegatives>
					<xr:MinValue xsi:nil="true"/>
					<xr:Synonym>
						<v8:item>
							<v8:lang>ru</v8:lang>
							<v8:content>Номер</v8:content>
						</v8:item>
					</xr:Synonym>
					<xr:Comment/>
					<xr:FullTextSearch>Use</xr:FullTextSearch>
					<xr:ChoiceParameterLinks/>
					<xr:FillValue xsi:nil="true"/>
					<xr:Mask/>
					<xr:ChoiceParameters/>
				</xr:StandardAttribute>
			</StandardAttributes>
			<ListPresentation/>
			<ExtendedListPresentation/>
			<Explanation/>
		</Properties>
		<ChildObjects>
			<Column uuid="323cdd10-901c-4e37-930c-c40695e9e1a1">
				<Properties>
					<Name>Организация</Name>
					<Synonym>
						<v8:item>
							<v8:lang>ru</v8:lang>
							<v8:content>Организация</v8:content>
						</v8:item>
					</Synonym>
					<Comment/>
					<Indexing>DontIndex</Indexing>
					<References>
						<xr:Item xsi:type="xr:MDObjectRef">Document.ЗаказПоставщику.Attribute.Организация</xr:Item>
						<xr:Item xsi:type="xr:MDObjectRef">Document.СчетФактураПолученный.Attribute.Организация</xr:Item>
						<xr:Item xsi:type="xr:MDObjectRef">Document.ПриходнаяНакладная.Attribute.Организация</xr:Item>
						<xr:Item xsi:type="xr:MDObjectRef">Document.ДополнительныеРасходы.Attribute.Организация</xr:Item>
						<xr:Item xsi:type="xr:MDObjectRef">Document.СчетНаОплатуПоставщика.Attribute.Организация</xr:Item>
						<xr:Item xsi:type="xr:MDObjectRef">Document.КорректировкаПоступления.Attribute.Организация</xr:Item>
					</References>
				</Properties>
			</Column>
			<Column uuid="ac386ab7-ccf6-4cb2-af87-5ff4e9230560">
				<Properties>
					<Name>ВидОперации</Name>
					<Synonym>
						<v8:item>
							<v8:lang>ru</v8:lang>
							<v8:content>Операция</v8:content>
						</v8:item>
					</Synonym>
					<Comment/>
					<Indexing>DontIndex</Indexing>
					<References>
						<xr:Item xsi:type="xr:MDObjectRef">Document.ЗаказПоставщику.Attribute.ВидОперации</xr:Item>
						<xr:Item xsi:type="xr:MDObjectRef">Document.СчетФактураПолученный.Attribute.ВидОперации</xr:Item>
						<xr:Item xsi:type="xr:MDObjectRef">Document.ПриходнаяНакладная.Attribute.ВидОперации</xr:Item>
						<xr:Item xsi:type="xr:MDObjectRef">Document.КорректировкаПоступления.Attribute.ВидОперации</xr:Item>
					</References>
				</Properties>
			</Column>
			<Column uuid="26788fcf-5a3d-453b-aab6-a4b053335e78">
				<Properties>
					<Name>Контрагент</Name>
					<Synonym>
						<v8:item>
							<v8:lang>ru</v8:lang>
							<v8:content>Контрагент</v8:content>
						</v8:item>
					</Synonym>
					<Comment/>
					<Indexing>DontIndex</Indexing>
					<References>
						<xr:Item xsi:type="xr:MDObjectRef">Document.ЗаказПоставщику.Attribute.Контрагент</xr:Item>
						<xr:Item xsi:type="xr:MDObjectRef">Document.СчетФактураПолученный.Attribute.Контрагент</xr:Item>
						<xr:Item xsi:type="xr:MDObjectRef">Document.ПриходнаяНакладная.Attribute.Контрагент</xr:Item>
						<xr:Item xsi:type="xr:MDObjectRef">Document.ДополнительныеРасходы.Attribute.Контрагент</xr:Item>
						<xr:Item xsi:type="xr:MDObjectRef">Document.СчетНаОплатуПоставщика.Attribute.Контрагент</xr:Item>
						<xr:Item xsi:type="xr:MDObjectRef">Document.КорректировкаПоступления.Attribute.Контрагент</xr:Item>
					</References>
				</Properties>
			</Column>
			<Column uuid="811373a4-18c7-4274-ac55-7de0acdf2137">
				<Properties>
					<Name>Договор</Name>
					<Synonym>
						<v8:item>
							<v8:lang>ru</v8:lang>
							<v8:content>Договор</v8:content>
						</v8:item>
					</Synonym>
					<Comment/>
					<Indexing>DontIndex</Indexing>
					<References>
						<xr:Item xsi:type="xr:MDObjectRef">Document.ЗаказПоставщику.Attribute.Договор</xr:Item>
						<xr:Item xsi:type="xr:MDObjectRef">Document.СчетФактураПолученный.Attribute.Договор</xr:Item>
						<xr:Item xsi:type="xr:MDObjectRef">Document.ПриходнаяНакладная.Attribute.Договор</xr:Item>
						<xr:Item xsi:type="xr:MDObjectRef">Document.ДополнительныеРасходы.Attribute.Договор</xr:Item>
						<xr:Item xsi:type="xr:MDObjectRef">Document.СчетНаОплатуПоставщика.Attribute.Договор</xr:Item>
						<xr:Item xsi:type="xr:MDObjectRef">Document.КорректировкаПоступления.Attribute.Договор</xr:Item>
					</References>
				</Properties>
			</Column>
			<Column uuid="f9996ee3-c7f1-4b38-8c8a-d33491973b9c">
				<Properties>
					<Name>ЗаказПоставщику</Name>
					<Synonym>
						<v8:item>
							<v8:lang>ru</v8:lang>
							<v8:content>Заказ поставщику</v8:content>
						</v8:item>
					</Synonym>
					<Comment/>
					<Indexing>DontIndex</Indexing>
					<References>
						<xr:Item xsi:type="xr:MDObjectRef">Document.ПриходнаяНакладная.Attribute.Заказ</xr:Item>
						<xr:Item xsi:type="xr:MDObjectRef">Document.ДополнительныеРасходы.Attribute.ЗаказПоставщику</xr:Item>
						<xr:Item xsi:type="xr:MDObjectRef">Document.КорректировкаПоступления.Attribute.Заказ</xr:Item>
					</References>
				</Properties>
			</Column>
			<Column uuid="9cd6031c-837c-4a95-a24e-90e2c04440c2">
				<Properties>
					<Name>НДС</Name>
					<Synonym>
						<v8:item>
							<v8:lang>ru</v8:lang>
							<v8:content>НДС</v8:content>
						</v8:item>
					</Synonym>
					<Comment/>
					<Indexing>DontIndex</Indexing>
					<References>
						<xr:Item xsi:type="xr:MDObjectRef">Document.СчетФактураПолученный.Attribute.СуммаНДСДокумента</xr:Item>
					</References>
				</Properties>
			</Column>
			<Column uuid="4675907b-ddf8-462c-a817-44d42ff72dd1">
				<Properties>
					<Name>Сумма</Name>
					<Synonym>
						<v8:item>
							<v8:lang>ru</v8:lang>
							<v8:content>Сумма</v8:content>
						</v8:item>
					</Synonym>
					<Comment/>
					<Indexing>DontIndex</Indexing>
					<References>
						<xr:Item xsi:type="xr:MDObjectRef">Document.ЗаказПоставщику.Attribute.СуммаДокумента</xr:Item>
						<xr:Item xsi:type="xr:MDObjectRef">Document.СчетФактураПолученный.Attribute.СуммаДокумента</xr:Item>
						<xr:Item xsi:type="xr:MDObjectRef">Document.ПриходнаяНакладная.Attribute.СуммаДокумента</xr:Item>
						<xr:Item xsi:type="xr:MDObjectRef">Document.ДополнительныеРасходы.Attribute.СуммаДокумента</xr:Item>
						<xr:Item xsi:type="xr:MDObjectRef">Document.СчетНаОплатуПоставщика.Attribute.СуммаДокумента</xr:Item>
						<xr:Item xsi:type="xr:MDObjectRef">Document.КорректировкаПоступления.Attribute.СуммаДокумента</xr:Item>
					</References>
				</Properties>
			</Column>
			<Column uuid="f89d360a-df99-4d09-a690-cd36324d1963">
				<Properties>
					<Name>Валюта</Name>
					<Synonym>
						<v8:item>
							<v8:lang>ru</v8:lang>
							<v8:content>Валюта</v8:content>
						</v8:item>
					</Synonym>
					<Comment/>
					<Indexing>DontIndex</Indexing>
					<References>
						<xr:Item xsi:type="xr:MDObjectRef">Document.ЗаказПоставщику.Attribute.ВалютаДокумента</xr:Item>
						<xr:Item xsi:type="xr:MDObjectRef">Document.СчетФактураПолученный.Attribute.ВалютаДокумента</xr:Item>
						<xr:Item xsi:type="xr:MDObjectRef">Document.ПриходнаяНакладная.Attribute.ВалютаДокумента</xr:Item>
						<xr:Item xsi:type="xr:MDObjectRef">Document.ДополнительныеРасходы.Attribute.ВалютаДокумента</xr:Item>
						<xr:Item xsi:type="xr:MDObjectRef">Document.СчетНаОплатуПоставщика.Attribute.ВалютаДокумента</xr:Item>
						<xr:Item xsi:type="xr:MDObjectRef">Document.КорректировкаПоступления.Attribute.ВалютаДокумента</xr:Item>
					</References>
				</Properties>
			</Column>
			<Column uuid="85f1a8d5-2df0-4300-9574-a4414f339ed0">
				<Properties>
					<Name>Ответственный</Name>
					<Synonym>
						<v8:item>
							<v8:lang>ru</v8:lang>
							<v8:content>Ответственный</v8:content>
						</v8:item>
					</Synonym>
					<Comment/>
					<Indexing>DontIndex</Indexing>
					<References>
						<xr:Item xsi:type="xr:MDObjectRef">Document.ДополнительныеРасходы.Attribute.Ответственный</xr:Item>
						<xr:Item xsi:type="xr:MDObjectRef">Document.ЗаказПоставщику.Attribute.Ответственный</xr:Item>
						<xr:Item xsi:type="xr:MDObjectRef">Document.ПриходнаяНакладная.Attribute.Ответственный</xr:Item>
						<xr:Item xsi:type="xr:MDObjectRef">Document.СчетНаОплатуПоставщика.Attribute.Ответственный</xr:Item>
						<xr:Item xsi:type="xr:MDObjectRef">Document.КорректировкаПоступления.Attribute.Ответственный</xr:Item>
					</References>
				</Properties>
			</Column>
			<Column uuid="a1b98556-d402-4839-b1a4-1ea058964e25">
				<Properties>
					<Name>НомерВходящегоДокумента</Name>
					<Synonym>
						<v8:item>
							<v8:lang>ru</v8:lang>
							<v8:content>№ вх. документа</v8:content>
						</v8:item>
					</Synonym>
					<Comment/>
					<Indexing>DontIndex</Indexing>
					<References>
						<xr:Item xsi:type="xr:MDObjectRef">Document.ДополнительныеРасходы.Attribute.НомерВходящегоДокумента</xr:Item>
						<xr:Item xsi:type="xr:MDObjectRef">Document.ЗаказПоставщику.Attribute.НомерВходящегоДокумента</xr:Item>
						<xr:Item xsi:type="xr:MDObjectRef">Document.ПриходнаяНакладная.Attribute.НомерВходящегоДокумента</xr:Item>
						<xr:Item xsi:type="xr:MDObjectRef">Document.СчетНаОплатуПоставщика.Attribute.НомерВходящегоДокумента</xr:Item>
						<xr:Item xsi:type="xr:MDObjectRef">Document.СчетФактураПолученный.Attribute.НомерПлатежноРасчетногоДокумента</xr:Item>
						<xr:Item xsi:type="xr:MDObjectRef">Document.КорректировкаПоступления.Attribute.НомерВходящегоДокумента</xr:Item>
					</References>
				</Properties>
			</Column>
			<Column uuid="8e7e37c3-9995-432f-a81d-a1f6b8083d26">
				<Properties>
					<Name>ДатаВходящегоДокумента</Name>
					<Synonym>
						<v8:item>
							<v8:lang>ru</v8:lang>
							<v8:content>Дата вх. документа</v8:content>
						</v8:item>
					</Synonym>
					<Comment/>
					<Indexing>DontIndex</Indexing>
					<References>
						<xr:Item xsi:type="xr:MDObjectRef">Document.ДополнительныеРасходы.Attribute.ДатаВходящегоДокумента</xr:Item>
						<xr:Item xsi:type="xr:MDObjectRef">Document.ЗаказПоставщику.Attribute.ДатаВходящегоДокумента</xr:Item>
						<xr:Item xsi:type="xr:MDObjectRef">Document.ПриходнаяНакладная.Attribute.ДатаВходящегоДокумента</xr:Item>
						<xr:Item xsi:type="xr:MDObjectRef">Document.СчетНаОплатуПоставщика.Attribute.ДатаВходящегоДокумента</xr:Item>
						<xr:Item xsi:type="xr:MDObjectRef">Document.СчетФактураПолученный.Attribute.ДатаПлатежноРасчетногоДокумента</xr:Item>
						<xr:Item xsi:type="xr:MDObjectRef">Document.КорректировкаПоступления.Attribute.ДатаВходящегоДокумента</xr:Item>
					</References>
				</Properties>
			</Column>
			<Column uuid="58c0e0cd-ae6b-46c1-8f3c-97644284697d">
				<Properties>
					<Name>Комментарий</Name>
					<Synonym>
						<v8:item>
							<v8:lang>ru</v8:lang>
							<v8:content>Комментарий</v8:content>
						</v8:item>
					</Synonym>
					<Comment/>
					<Indexing>DontIndex</Indexing>
					<References>
						<xr:Item xsi:type="xr:MDObjectRef">Document.ЗаказПоставщику.Attribute.Комментарий</xr:Item>
						<xr:Item xsi:type="xr:MDObjectRef">Document.СчетФактураПолученный.Attribute.Комментарий</xr:Item>
						<xr:Item xsi:type="xr:MDObjectRef">Document.ПриходнаяНакладная.Attribute.Комментарий</xr:Item>
						<xr:Item xsi:type="xr:MDObjectRef">Document.ДополнительныеРасходы.Attribute.Комментарий</xr:Item>
						<xr:Item xsi:type="xr:MDObjectRef">Document.СчетНаОплатуПоставщика.Attribute.Комментарий</xr:Item>
						<xr:Item xsi:type="xr:MDObjectRef">Document.КорректировкаПоступления.Attribute.Комментарий</xr:Item>
					</References>
				</Properties>
			</Column>
			<Column uuid="ba369f25-99ba-43a5-aec0-22af82927c93">
				<Properties>
					<Name>Автор</Name>
					<Synonym>
						<v8:item>
							<v8:lang>ru</v8:lang>
							<v8:content>Автор</v8:content>
						</v8:item>
					</Synonym>
					<Comment/>
					<Indexing>DontIndex</Indexing>
					<References>
						<xr:Item xsi:type="xr:MDObjectRef">Document.ДополнительныеРасходы.Attribute.Автор</xr:Item>
						<xr:Item xsi:type="xr:MDObjectRef">Document.ЗаказПоставщику.Attribute.Автор</xr:Item>
						<xr:Item xsi:type="xr:MDObjectRef">Document.ПриходнаяНакладная.Attribute.Автор</xr:Item>
						<xr:Item xsi:type="xr:MDObjectRef">Document.СчетНаОплатуПоставщика.Attribute.Автор</xr:Item>
						<xr:Item xsi:type="xr:MDObjectRef">Document.СчетФактураПолученный.Attribute.Автор</xr:Item>
						<xr:Item xsi:type="xr:MDObjectRef">Document.КорректировкаПоступления.Attribute.Автор</xr:Item>
					</References>
				</Properties>
			</Column>
			<Column uuid="87171c6a-c976-4a8a-81cc-7f0df70a9bfb">
				<Properties>
					<Name>Склад</Name>
					<Synonym>
						<v8:item>
							<v8:lang>ru</v8:lang>
							<v8:content>Склад</v8:content>
						</v8:item>
					</Synonym>
					<Comment/>
					<Indexing>DontIndex</Indexing>
					<References>
						<xr:Item xsi:type="xr:MDObjectRef">Document.ПриходнаяНакладная.Attribute.СтруктурнаяЕдиница</xr:Item>
						<xr:Item xsi:type="xr:MDObjectRef">Document.КорректировкаПоступления.Attribute.СтруктурнаяЕдиница</xr:Item>
						<xr:Item xsi:type="xr:MDObjectRef">Document.ЗаказПоставщику.Attribute.СтруктурнаяЕдиницаРезерв</xr:Item>
						<xr:Item xsi:type="xr:MDObjectRef">Document.ДополнительныеРасходы.Attribute.СтруктурнаяЕдиница</xr:Item>
					</References>
				</Properties>
			</Column>
			<Form>ФормаСписка</Form>
			<Command uuid="2da44ba1-464a-4164-9db2-5f5cdd250e00">
				<Properties>
					<Name>ОткрытьЖурналЗакупокРазделГлавное</Name>
					<Synonym>
						<v8:item>
							<v8:lang>ru</v8:lang>
							<v8:content>Закупки</v8:content>
						</v8:item>
					</Synonym>
					<Comment/>
					<Group>NavigationPanelOrdinary</Group>
					<CommandParameterType/>
					<ParameterUseMode>Single</ParameterUseMode>
					<ModifiesData>false</ModifiesData>
					<Representation>Auto</Representation>
					<ToolTip/>
					<Picture/>
					<Shortcut/>
					<OnMainServerUnavalableBehavior>Auto</OnMainServerUnavalableBehavior>
				</Properties>
			</Command>
		</ChildObjects>
	</DocumentJournal>
</MetaDataObject>